{"Progressive Caucus": ["Pramila Jayapal", "Katie Porter", "Ilhan Omar", "Raul Grijalva", "Barbara Lee", "Mark Pocan", "Jamie Raskin", "Joe Neguse", "Marie Newman", "Sheila Jackson Lee", "Donald Norcross", "Rashida Tlaib", "David Cicilline", "Jesus Garcia", "Bonnie Watson Coleman", "Cori Bush", "Debbie Dingell", "Veronica Escobar", "Mondaire Jones", "Ro Khanna", "Lloyd Doggett", "Andy Levin", "Mark Takano", "Adriano Espaillat", "Jamaal Bowman", "Teresa Leger Fernandez", "Bernie Sanders", "Jan Schakowsky", "Alma Adams", "Nanette Barragan", "Karen Bass", "Eddie Bernice Johnson", "Don Beyer", "Earl Blumenauer", "Lisa Blunt Rochester", "Suzanne Bonamici", "Brendan Boyle", "Andre Carson", "Matt Cartwright", "Judy Chu", "Katherine Clark", "Yvette Clarke", "Steve Cohen", "Madeleine Dean", "Peter DeFazio", "Diana DeGette", "Rosa DeLauro", "Mark DeSaulnier", "Dwight Evans", "Lois Frankel", "Ruben Gallego", "Sylvia Garcia", "Jimmy Gomez", "Eleanor Holmes Norton", "Steven Horsford", "Jared Huffman", "Hakeem Jeffries", "Hank Johnson", "Kai Kahele", "Dan Kildee", "Andy Kim", "Brenda Lawrence", "Mike Levin", "Ted Lieu", "Zoe Lofgren", "Alan Lowenthal", "Carolyn Maloney", "James McGovern", "Grace Meng", "Gwen Moore", "Joe Morelle", "Jerrold Nadler", "Grace Napolitano", "Alexandria Ocasio-Cortez", "Frank Pallone", "Jimmy Panetta", "Chellie Pingree", "Ayanna Pressley", "Linda Sanchez", "Mary Gay Scanlon", "Brad Sherman", "Adam Smith", "Darren Soto", "Ritchie Torres", "Lori Trahan", "Juan Vargas", "Nydia Velazquez", "Maxine Waters", "Peter Welch", "Nikema Williams", "Frederica Wilson", "John Yarmuth"], "New Democratic Coalition": ["Suzan DelBene", "Ami Bera", "Sharice Davids", "Ann McLane Kuster", "Scott Peters", "Stacey Plaskett", "Chrissy Houlahan", "Terri Sewell", "Ann Kirkpatrick", "Tom O'Halleran", "Greg Stanton", "Pete Aguilar", "Julia Brownley", "Salud Carbajal", "Tony Cardenas", "Lou Correa", "Jim Costa", "Josh Harder", "Sara Jacobs", "Jimmy Panetta", "Raul Ruiz", "Adam Schiff", "Norma Torres", "Juan Vargas", "Jason Crow", "Ed Perlmutter", "Jim Himes", "Lisa Blunt Rochester", "Charlie Crist", "Val Demings", "Al Lawson", "Stephanie Murphy", "Darren Soto", "Debbie Wasserman Schultz", "Carolyn Bourdeaux", "Lucy McBath", "David Scott", "Nikema Williams", "Ed Case", "Cheri Bustos", "Sean Casten", "Bill Foster", "Raja Krishnamoorthi", "Mike Quigley", "Brad Schneider", "Andre Carson", "Frank Mrvan", "Cindy Axne", "Troy Carter", "Anthony Brown", "David Trone", "Bill Keating", "Seth Moulton", "Lori Trahan", "Brenda Lawrence", "Elissa Slotkin", "Haley Stevens", "Angie Craig", "Dean Phillips", "Steven Horsford", "Susie Lee", "Chris Pappas", "Josh Gottheimer", "Tom Malinowski", "Donald Norcross", "Mikie Sherrill", "Sean Patrick Maloney", "Gregory Meeks", "Joe Morelle", "Kathleen Rice", "Thomas Suozzi", "Kathy Manning", "Deborah Ross", "Shontel Brown", "Kurt Schrader", "Brendan Boyle", "Madeleine Dean", "Chrissy Houlahan", "Susan Wild", "Jim Cooper", "Colin Allred", "Joaquin Castro", "Henry Cuellar", "Veronica Escobar", "Lizzie Fletcher", "Vincente Gonzalez", "Marc Veasey", "Don Beyer", "Gerry Connolly", "Elaine Luria", "Donald McEachin", "Abigail Spanberger", "Jennifer Wexton", "Derek Kilmer", "Rick Larsen", "Kim Schrier", "Adam Smith", "Marilyn Strickland"], "Freedom Caucus": ["Andy Biggs", "Dan Bishop", "Lauren Boebert", "Mo Brooks", "Ken Buck", "Ted Budd", "Ben Cline", "Michael Cloud", "Andrew Clyde", "Madison Cawthorn", "Warren Davidson", "Scott DesJarlais", "Byron Donalds", "Jeff Duncan", "Russ Fulcher", "Louie Gohmert", "Bob Good", "Paul Gosar", "Mark Green", "Morgan Griffith", "Andy Harris", "Diana Harshbarger", "Yvette Herrell", "Jody Hice", "Clay Higgins", "Jim Jordan", "Debbie Lesko", "Mary Miller", "Alex Mooney", "Barry Moore", "Ralph Norman", "Gary Palmer", "Bill Posey", "Matthew Rosendale", "Chip Roy", "David Schweikert", "Greg Steube", "Thomas Tiffany", "Randy Weber"], "Republican Governance Group": ["Adam Kinzinger", "Andrew Garbarino", "Beth Van Duyne", "Bill Johnson", "Blake Moore", "Brian Fitzpatrick", "Bryan Steil", "Carlos Gimenez", "Cathy McMorris Rodgers", "Chris Jacobs", "Chris Smith", "Cliff Bentz", "David Joyce", "David McKinley", "David Valadao", "Don Bacon", "Elise Stefanik", "Fred Upton", "Glenn Thompson", "Jaime Herrera Beutler", "Jay Obernolte", "Jefferson Van Drew", "Jenniffer Gonzalez-Colon", "John Curtis", "John Katko", "Kelly Armstrong", "Maria Salazar", "Mariannette Miller-Meeks", "Mario Diaz-Balart","Mark Amodei", "Michael Burgess", "Michelle Steel", "Mike Bost", "Mike Gallagher", "Michael McCaul", "Mike Turner", "Nancy Mace", "Nicole Malliotakis", "Pete Stauber", "Peter Meijer", "Rodney Davis", "Steve Womack", "Tom Rice", "Troy Balderson", "Young Kim"], "Republican Study Committee": ["Alex Mooney", "Andrew Clyde", "Andy Barr", "Ann Wagner", "Ashley Hinson", "August Pfluger", "Austin Scott", "Barry Loudermilk", "Barry Moore", "Ben Cline", "Beth Van Duyne", "Bill Huizenga", "Bill Johnson", "Bill Posey", "Blaine Luetkemeyer", "Blake Moore", "Bob Gibbs", "Bob Good", "Robert Latta", "Brad Wenstrup", "Brett Guthrie", "Brian Babin", "Brian Mast", "Bruce Westerman", "Bryan Steil", "Buddy Carter", "Burgess Owens", "Byron Donalds", "Carlos Gimenez", "Cathy McMorris Rodgers", "Chip Roy", "Chris Jacobs", "Chris Stewart", "Chuck Fleischmann", "Claudia Tenney", "Clay Higgins", "Cliff Bentz", "Dan Bishop", "Dan Crenshaw", "Daniel Meuser", "Dan Newhouse", "Daniel Webster", "Darin LaHood", "Darrell Issa", "David Kustoff", "David McKinley", "David Rouzer", "David Schweikert", "Debbie Lesko", "Diana Harshbarger", "Don Bacon", "Doug LaMalfa", "Doug Lamborn", "Drew Ferguson", "Dusty Johnson", "Elise Stefanik", "Fred Keller", "French Hill", "Garret Graves", "Gary Palmer", "Glenn Grothman", "Gregory Murphy", "Greg Steube", "Gus Bilirakis", "Guy Reschenthaler", "Jack Bergman", "Jackie Walorski", "Jake LaTurner", "James Comer", "Jason Smith", "Jay Obernolte", "Jeff Duncan", "Jerry Carl", "Jim Baird", "Jim Banks", "Jodey Arrington", "Jody Hice", "Joe Wilson", "John Carter", "John Curtis", "John Joyce", "John Moolenaar", "John Rose", "Julia Letlow", "Kat Cammack", "Kay Granger", "Kelly Armstrong", "Ken Buck", "Kevin Brady", "Kevin Hern", "Lance Gooden", "Larry Bucshon", "Lauren Boebert", "Lisa McClain", "Lloyd Smucker", "Madison Cawthorn", "Marjorie Taylor Greene", "Mark Green", "Markwayne Mullin", "Mary Miller", "Matthew Rosendale", "Michael Burgess", "Michael Cloud", "Michael McCaul", "Michael Waltz", "Michelle Fischbach", "Mike Bost", "Mike Carey", "Mike Gallagher", "Mike Garcia", "Mike Johnson", "Mike Kelly", "Mike Rogers", "Mike Turner", "Neal Dunn", "Nicole Malliotakis", "Pat Fallon", "Patrick McHenry", "Paul Gosar", "Pete Stauber", "Ralph Norman", "Randy Feenstra", "Randy Weber", "Richard Hudson", "Rick Allen", "Robert Wittman", "Robert Aderholt", "Roger Williams", "Ron Estes", "Ronny Jackson", "Russ Fulcher", "Scott DesJarlais", "Scott Franklin", "Scott Fitzgerald", "Steve Chabot", "Steve Scalise", "Steven Palazzo", "Ted Budd", "Tim Burchett", "Tim Walberg", "Tom Cole", "Tom Emmer", "Tom McClintock", "Tom Reed", "Tom Rice", "Thomas Tiffany", "Tony Gonzales", "Tracey Mann", "Trent Kelly", "Troy Balderson", "Troy Nehls", "Van Taylor", "Vern Buchanan", "Vicky Hartzler", "Victoria Spartz", "Virginia Foxx", "Warren Davidson", "William Timmons", "Yvette Herrell"], "Problem Solvers Caucus": ["Abigail Spanberger", "Andrew Garbarino", "Anthony Gonzalez", "Ben Cline", "Bill Johnson", "Brad Schneider", "Brian Fitzpatrick", "Bryan Steil", "Carolyn Bourdeaux", "Chris Smith", "Chrissy Houlahan", "Conor Lamb", "Daniel Meuser", "Darren Soto", "David Joyce", "Dean Phillips", "Debbie Dingell", "Don Bacon", "Dusty Johnson", "Elaine Luria", "Elissa Slotkin", "Fred Upton", "Haley Stevens", "Jaime Herrera Beutler", "Jared Golden", "Jenniffer Gonzalez-Colon", "Jim Costa", "Jimmy Panetta", "John Curtis", "John Katko", "Josh Harder", "Kurt Schrader", "Lloyd Smucker", "Lou Correa", "Mark Amodei", "Mike Bost", "Mike Gallagher", "Pete Stauber", "Peter Meijer", "Salud Carbajal", "Scott Peters", "Stephanie Murphy", "Steven Horsford", "Susie Lee", "Thomas Suozzi", "Tom Malinowski", "Tom O'Halleran", "Tom Rice", "Tony Gonzales", "Van Taylor", "Vicente Gonzalez", "Young Kim"]}